devtools_json_to_ts/__init__.py
devtools_json_to_ts-1.0.1.dist-info/METADATA
devtools_json_to_ts-1.0.1.dist-info/WHEEL
devtools_json_to_ts-1.0.1.dist-info/top_level.txt
devtools_json_to_ts-1.0.1.dist-info/RECORD
