Metadata-Version: 2.1
Name: devtools_json_to_ts
Version: 1.0.1
Summary: JSON to TypeScript converter
Home-page: https://devtools.at/tools/json-to-typescript
Author: DevTools.at
Author-email: hello@devtools.at
Project-URL: Homepage, https://devtools.at/tools/json-to-typescript
Project-URL: Repository, https://github.com/devtools-at/json-to-typescript
Classifier: Development Status :: 4 - Beta
Classifier: Intended Audience :: Developers
Classifier: License :: OSI Approved :: MIT License
Classifier: Programming Language :: Python :: 3
Requires-Python: >=3.8
